tests/core/__init__.py
tests/core/test_block_manager.py
tests/core/test_scheduler.py
tests/core/utils.py
tests/lora/__init__.py
tests/lora/conftest.py
tests/lora/test_gemma.py
tests/lora/test_layer_variation.py
tests/lora/test_layers.py
tests/lora/test_llama.py
tests/lora/test_lora.py
tests/lora/test_lora_manager.py
tests/lora/test_mixtral.py
tests/lora/test_punica.py
tests/lora/test_tokenizer.py
tests/lora/test_tokenizer_group.py
tests/lora/test_utils.py
tests/lora/test_worker.py
tests/lora/utils.py
tests/spec_decode/__init__.py
tests/spec_decode/test_batch_expansion.py
tests/spec_decode/test_metrics.py
tests/spec_decode/test_multi_step_worker.py
tests/spec_decode/test_spec_decode_worker.py
tests/spec_decode/test_utils.py
tests/spec_decode/utils.py
tests/tokenization/__init__.py
tests/tokenization/test_cached_tokenizer.py
tests/tokenization/test_detokenize.py
tests/tokenization/test_tokenizer_group.py
tests/worker/__init__.py
tests/worker/test_model_runner.py
tests/worker/test_swap.py
tests/worker/spec_decode/__init__.py
tests/worker/spec_decode/test_multi_step_worker.py
tests/worker/spec_decode/utils.py
tilearn/__init__.py
tilearn/infer/__init__.py
tilearn/infer/vllm/__init__.py
vllm/_C.cpython-310-x86_64-linux-gnu.so
vllm/_C.cpython-39-x86_64-linux-gnu.so
vllm/__init__.py
vllm/activation_ops.cpython-310-x86_64-linux-gnu.so
vllm/attention_ops.cpython-310-x86_64-linux-gnu.so
vllm/block.py
vllm/cache_ops.cpython-310-x86_64-linux-gnu.so
vllm/config.cpython-310-x86_64-linux-gnu.so
vllm/cuda_utils.cpython-310-x86_64-linux-gnu.so
vllm/layernorm_ops.cpython-310-x86_64-linux-gnu.so
vllm/logger.py
vllm/outputs.py
vllm/pos_encoding_ops.cpython-310-x86_64-linux-gnu.so
vllm/prefix.py
vllm/py.typed
vllm/quantization_ops.cpython-310-x86_64-linux-gnu.so
vllm/sampling_params.py
vllm/sequence.py
vllm/test_utils.py
vllm/utils.py
vllm/core/__init__.py
vllm/core/block_manager.py
vllm/core/evictor.py
vllm/core/policy.py
vllm/core/scheduler.py
vllm/engine/__init__.py
tilearn_infer-0.3.3.dist-info/LICENSE
tilearn_infer-0.3.3.dist-info/METADATA
tilearn_infer-0.3.3.dist-info/WHEEL
tilearn_infer-0.3.3.dist-info/top_level.txt
tilearn_infer-0.3.3.dist-info/RECORD
