Metadata-Version: 2.1
Name: tilearn-infer
Version: 0.3.3
Summary: A high-throughput and memory-efficient inference and serving engine for LLMs
Home-page: https://github.com/vllm-project/vllm
Author: vLLM Team
License: Apache 2.0
Project-URL: Homepage, https://github.com/vllm-project/vllm
Project-URL: Documentation, https://vllm.readthedocs.io/en/latest/
Classifier: Programming Language :: Python :: 3.8
Classifier: Programming Language :: Python :: 3.9
Classifier: Programming Language :: Python :: 3.10
Classifier: Programming Language :: Python :: 3.11
Classifier: License :: OSI Approved :: Apache Software License
Classifier: Topic :: Scientific/Engineering :: Artificial Intelligence
Requires-Python: >=3.8
License-File: LICENSE
Requires-Dist: cmake >=3.21
Requires-Dist: ninja
Requires-Dist: psutil
Requires-Dist: ray >=2.9
Requires-Dist: sentencepiece
Requires-Dist: numpy
Requires-Dist: torch ==2.1.2
Requires-Dist: transformers >=4.39.1
Requires-Dist: xformers ==0.0.23.post1
Requires-Dist: fastapi
Requires-Dist: uvicorn[standard]
Requires-Dist: pydantic >=2.0
Requires-Dist: prometheus-client >=0.18.0
Requires-Dist: pynvml ==11.5.0
Requires-Dist: triton >=2.1.0
Requires-Dist: outlines ==0.0.34
Requires-Dist: cupy-cuda12x ==12.1.0
